MANIFEST.in
README.md
setup.py
website_poller.egg-info/PKG-INFO
website_poller.egg-info/SOURCES.txt
website_poller.egg-info/dependency_links.txt
website_poller.egg-info/entry_points.txt
website_poller.egg-info/requires.txt
website_poller.egg-info/top_level.txt
websitepoller/__init__.py
websitepoller/poller.py