Metadata-Version: 1.0
Name: website-poller
Version: 0.5.4
Summary: Polls specified websites and alerts using system notifications.
Home-page: http://koodilehto.github.com/website-poller
Author: Koodilehto osk.
Author-email: info@koodilehto.fi
License: MIT
Platform: UNKNOWN
Classifier: Development Status :: 4 - Beta
Classifier: Environment :: Console
Classifier: Intended Audience :: Developers
Classifier: Intended Audience :: System Administrators
Classifier: License :: OSI Approved :: MIT License
Classifier: Operating System :: POSIX
Classifier: Programming Language :: Python
Classifier: Topic :: Internet
Classifier: Topic :: Internet :: WWW/HTTP
Classifier: Topic :: System :: Networking :: Monitoring
